liquiphy_gui/__init__.py
liquiphy_gui-1.0.0.dist-info/entry_points.txt
liquiphy_gui-1.0.0.dist-info/LICENSE
liquiphy_gui-1.0.0.dist-info/WHEEL
liquiphy_gui-1.0.0.dist-info/METADATA
liquiphy_gui-1.0.0.dist-info/RECORD
