Metadata-Version: 2.1
Name: liquiphy_gui
Version: 1.0.0
Summary: A simple graphical front-end to liquidsfz.
Author-email: Leon Dionne <ldionne@dridesign.sh.cn>
Classifier: License :: OSI Approved :: GNU General Public License v3 or later (GPLv3+)
Classifier: Programming Language :: Python
Classifier: Programming Language :: Python :: 3.10
Classifier: Topic :: Multimedia :: Sound/Audio :: Sound Synthesis
Classifier: Topic :: Multimedia :: Sound/Audio :: MIDI
Requires-Dist: PyQt5
Requires-Dist: conn_jack >= 1.2.0
Requires-Dist: liquiphy
Requires-Dist: soso_qt_extras >= 1.2.0
Project-URL: Home, https://github.com/Zen-Master-SoSo/liquiphy_gui
